Sudip_snpdw/__init__.py
Sudip_snpdw-0.1.dist-info/METADATA
Sudip_snpdw-0.1.dist-info/WHEEL
Sudip_snpdw-0.1.dist-info/top_level.txt
Sudip_snpdw-0.1.dist-info/RECORD
