Metadata-Version: 2.1
Name: Sudip-snpdw
Version: 0.1
Summary: This package helps in automating downloads from snp-seek data base
Author: Sudipan Paul
Author-email: <sudipanpaul6@gmail.com>
Requires-Dist: webdriver-manager
Requires-Dist: selenium
Requires-Dist: pandas
